[
  {
    "id": 1,
    "category": "Frontend",
    "skills": [
      {
        "id": 1,
        "title": "HTML/Pug"
      },
      {
        "id": 2,
        "title": "CSS/SCSS"
      },
      {
        "id": 3,
        "title": "JavaScript(ES6+)"
      },
      {
        "id": 4,
        "title": "Vue.js"
      }
    ]
  },
  {
    "id": 2,
    "category": "Work Flow",
    "skills": [
      {
        "id": 1,
        "title": "Git"
      },
      {
        "id": 2,
        "title": "Terminal"
      },
      {
        "id": 3,
        "title": "Gulp"
      },
      {
        "id": 4,
        "title": "Webpack"
      }
    ]
  },
  {
    "id": 3,
    "category": "Languages",
    "skills": [
      {
        "id": 1,
        "title": "Russian"
      },
      {
        "id": 2,
        "title": "English"
      }
    ]
  }
]
